paperchill/__init__.py
paperchill/chatbot.py
paperchill/pdf_convert.py
paperchill/templates/summary_with_questions.html
paperchill/templates/upload_form.html
paperchill/with_logger.py
paperchill/wrapp.py
paperchill-0.1.0.dist-info/METADATA
paperchill-0.1.0.dist-info/WHEEL
paperchill-0.1.0.dist-info/RECORD
